{"mc":{
	"boy_clear":{
		"frameRate":24,
		"events":[
			
			],
		"frames":[
			
			{
			"res":"87DE68A9",
			"x":-72,
			"y":-142,
			"duration":49
			},
			{
			"res":"D264C203",
			"x":-61,
			"y":-158
			}
			]
},"boy_stand":{
		"frameRate":24,
		"events":[
			
			],
		"frames":[
			
			{
			"res":"87DE68A9",
			"x":-72,
			"y":-142
			}
			]
},"fuku_clear":{
		"frameRate":24,
		"events":[
			
			],
		"frames":[
			
			{
			"res":"5E2A9EEA",
			"x":-82,
			"y":-142,
			"duration":35
			},
			{
			"res":"2DC642D8",
			"x":-70,
			"y":-160,
			"duration":25
			}
			]
},"pokapoka":{
		"frameRate":24,
		"events":[
			
			],
		"frames":[
			
			{
			"res":"3B2EDEA0",
			"x":-82,
			"y":-130,
			"duration":3
			},
			{
			"res":"C2A650A",
			"x":-104,
			"y":-133,
			"duration":3
			}
			]
},"wresler_stand":{
		"frameRate":24,
		"events":[
			
			],
		"frames":[
			
			{
			"res":"A5CCB784",
			"x":-103,
			"y":-152
			}
			]
},"fuku_attack":{
		"frameRate":24,
		"events":[
			
			],
		"frames":[
			
			{
			"res":"CF62935B",
			"x":-45,
			"y":-212,
			"duration":3
			},
			{
			"res":"B1C658BE",
			"x":-60,
			"y":-183,
			"duration":2
			},
			{
			"res":"56B49F32",
			"x":-73,
			"y":-163,
			"duration":2
			},
			{
			"res":"DC7EC58C",
			"x":-121,
			"y":-146,
			"duration":4
			},
			{
			"res":"89DE1AD2",
			"x":-121,
			"y":-141,
			"duration":3
			},
			{
			"res":"DC7EC58C",
			"x":-121,
			"y":-146,
			"duration":3
			},
			{
			"res":"89DE1AD2",
			"x":-121,
			"y":-141,
			"duration":3
			},
			{
			"res":"DC7EC58C",
			"x":-121,
			"y":-146,
			"duration":3
			},
			{
			"res":"89DE1AD2",
			"x":-121,
			"y":-141,
			"duration":3
			},
			{
			"res":"DC7EC58C",
			"x":-121,
			"y":-146,
			"duration":3
			},
			{
			"res":"89DE1AD2",
			"x":-121,
			"y":-141,
			"duration":9
			},
			{
			"res":"2144DF1C",
			"x":0,
			"y":0
			}
			]
},"fuku_roll":{
		"frameRate":24,
		"events":[
			
			],
		"frames":[
			
			{
			"res":"70B26718",
			"x":-96,
			"y":-125
			},
			{
			"res":"31E32624",
			"x":-99,
			"y":-142,
			"duration":2
			},
			{
			"res":"E93AB5A1",
			"x":-80,
			"y":-131,
			"duration":2
			}
			]
},"wresler_cry":{
		"frameRate":24,
		"events":[
			
			],
		"frames":[
			
			{
			"res":"C76CA1E6",
			"x":-57,
			"y":-93,
			"duration":2
			},
			{
			"res":"45E2DA38",
			"x":-57,
			"y":-95,
			"duration":2
			}
			]
},"wresler_damage":{
		"frameRate":24,
		"events":[
			
			],
		"frames":[
			
			{
			"res":"59C7C603",
			"x":-143,
			"y":-187,
			"duration":14
			},
			{
			"res":"EA259641",
			"x":-140,
			"y":94
			}
			]
},"boy_move":{
		"frameRate":24,
		"events":[
			
			],
		"frames":[
			
			{
			"res":"1583F5F9",
			"x":-75,
			"y":-131,
			"duration":10
			},
			{
			"res":"6F53E0B3",
			"x":-80,
			"y":-129,
			"duration":3
			}
			]
},"wresler_move":{
		"frameRate":24,
		"events":[
			
			],
		"frames":[
			
			{
			"res":"41ADEDD6",
			"x":-87,
			"y":-130,
			"duration":13
			},
			{
			"res":"D1BC895",
			"x":-104,
			"y":-135,
			"duration":2
			}
			]
}},
	"res":{
		"CF62935B":{"x":322,"y":1064,"w":91,"h":287},
		"D264C203":{"x":677,"y":535,"w":152,"h":300},
		"45E2DA38":{"x":911,"y":1,"w":112,"h":189},
		"31E32624":{"x":703,"y":268,"w":198,"h":265},
		"C76CA1E6":{"x":333,"y":857,"w":111,"h":189},
		"A5CCB784":{"x":286,"y":1,"w":203,"h":303},
		"E93AB5A1":{"x":1,"y":378,"w":180,"h":268},
		"2144DF1C":{"x":656,"y":837,"w":1,"h":1},
		"1583F5F9":{"x":831,"y":834,"w":154,"h":265},
		"41ADEDD6":{"x":491,"y":287,"w":184,"h":282},
		"D1BC895":{"x":491,"y":1,"w":210,"h":284},
		"3B2EDEA0":{"x":183,"y":560,"w":181,"h":262},
		"5E2A9EEA":{"x":511,"y":571,"w":143,"h":282},
		"6F53E0B3":{"x":831,"y":571,"w":158,"h":261},
		"B1C658BE":{"x":903,"y":268,"w":107,"h":260},
		"EA259641":{"x":1,"y":1064,"w":319,"h":107},
		"2DC642D8":{"x":1,"y":648,"w":152,"h":300},
		"56B49F32":{"x":689,"y":837,"w":124,"h":241},
		"59C7C603":{"x":1,"y":1,"w":283,"h":375},
		"C2A650A":{"x":703,"y":1,"w":206,"h":265},
		"70B26718":{"x":286,"y":306,"w":202,"h":252},
		"89DE1AD2":{"x":511,"y":855,"w":176,"h":221},
		"DC7EC58C":{"x":155,"y":837,"w":176,"h":225},
		"87DE68A9":{"x":366,"y":571,"w":143,"h":284}
	}}